{
    "ac-fill": 61697,
    "ac-line": 61698,
    "adapter-fill": 61699,
    "adapter-line": 61700,
    "adjoining-room-fill": 61701,
    "adjoining-room-line": 61702,
    "aerobics-fill": 61703,
    "aerobics-line": 61704,
    "air-filter-fill": 61705,
    "air-filter-line": 61706,
    "alarm-fill": 61707,
    "alarm-line": 61708,
    "area-fill": 61709,
    "area-line": 61710,
    "atm-fill": 61711,
    "atm-line": 61712,
    "baby-dress-fill": 61713,
    "baby-dress-line": 61714,
    "baby-fill": 61715,
    "baby-line": 61716,
    "baby-slash-fill": 61717,
    "baby-slash-line": 61718,
    "ball-fill": 61719,
    "ball-line": 61720,
    "bank-fill": 61721,
    "bank-line": 61722,
    "bar-fill": 61723,
    "bar-line": 61724,
    "basket-fill": 61725,
    "basket-line": 61726,
    "bathrobe-fill": 61727,
    "bathrobe-line": 61728,
    "bbq-fill": 61729,
    "bbq-line": 61730,
    "beach-fill": 61731,
    "beach-line": 61732,
    "bed-fill": 61733,
    "bed-line": 61734,
    "bell-boy-fill": 61735,
    "bell-boy-line": 61736,
    "bill-fill": 61737,
    "bill-line": 61738,
    "billiards-fill": 61739,
    "billiards-line": 61740,
    "bin-fill": 61741,
    "bin-line": 61742,
    "bingo-fill": 61743,
    "bingo-line": 61744,
    "blanket-fill": 61745,
    "blanket-line": 61746,
    "boat-fill": 61747,
    "boat-line": 61748,
    "bon-fire-fill": 61749,
    "bon-fire-line": 61750,
    "books-fill": 61751,
    "books-line": 61752,
    "bowl-fill": 61753,
    "bowl-line": 61754,
    "box-fill": 61755,
    "box-line": 61756,
    "briefcase-fill": 61757,
    "briefcase-line": 61758,
    "broom-fill": 61759,
    "broom-line": 61760,
    "building-fill": 61761,
    "building-line": 61762,
    "burger-fill": 61763,
    "burger-line": 61764,
    "cab-fill": 61765,
    "cab-line": 61766,
    "call-bell-fill": 61767,
    "call-bell-line": 61768,
    "cards-fill": 61769,
    "cards-line": 61770,
    "carpet-fill": 61771,
    "carpet-line": 61772,
    "catering-fill": 61773,
    "catering-line": 61774,
    "cell-fill": 61775,
    "cell-line": 61776,
    "chair-fill": 61777,
    "chair-line": 61778,
    "charging-station-fill": 61779,
    "charging-station-line": 61780,
    "chat-fill": 61781,
    "chat-line": 61782,
    "check-in-fill": 61783,
    "check-in-line": 61784,
    "check-out-fill": 61785,
    "check-out-line": 61786,
    "chef-hat-fill": 61787,
    "chef-hat-line": 61788,
    "cheque-fill": 61789,
    "cheque-line": 61790,
    "chicken-fill": 61791,
    "chicken-line": 61792,
    "clock-fill": 61793,
    "clock-line": 61794,
    "coffee-cup-fill": 61795,
    "coffee-line": 61796,
    "coffee-machine-fill": 61797,
    "coffee-machine-line": 61798,
    "coking-pot-fill": 61799,
    "coking-pot-line": 61800,
    "conference-fill": 61801,
    "conference-line": 61802,
    "corridor-fill": 61803,
    "corridor-line": 61804,
    "court-fill": 61805,
    "court-line": 61806,
    "cpu-fill": 61807,
    "cpu-line": 61808,
    "currency-fill": 61809,
    "currency-line": 61810,
    "cycle-fill": 61811,
    "cycle-line": 61812,
    "data-port-fill": 61813,
    "data-port-line": 61814,
    "diet-fill": 61815,
    "diet-line": 61816,
    "disco-fill": 61817,
    "disco-line": 61818,
    "discount-fill": 61819,
    "discount-line": 61820,
    "dish-fill": 61821,
    "dish-line": 61822,
    "dispencer-fill": 61823,
    "dispencer-line": 61824,
    "door-fill": 61825,
    "door-line": 61826,
    "door-man-fill": 61827,
    "door-man-line": 61828,
    "dress-fill": 61829,
    "dress-line": 61830,
    "drop-fill": 61831,
    "drop-line": 61832,
    "dry-clean-fill": 61833,
    "dry-clean-line": 61834,
    "dryer-fill": 61835,
    "dryer-line": 61836,
    "electric-outlet-fill": 61837,
    "electric-outlet-line": 61838,
    "fan-fill": 61839,
    "fan-line": 61840,
    "fence-fill": 61841,
    "fence-line": 61842,
    "ferry-fill": 61843,
    "ferry-line": 61844,
    "fire-extinguisher-fill": 61845,
    "fire-extinguisher-line": 61846,
    "flash-fill": 61847,
    "flash-line": 61848,
    "flower-fill": 61849,
    "flower-line": 61850,
    "front-office-fill": 61851,
    "front-office-line": 61852,
    "game-fill": 61853,
    "game-line": 61854,
    "gas-station-fill": 61855,
    "gas-station-line": 61856,
    "gender-female-fill": 61857,
    "gender-female-line": 61858,
    "gift-fill": 61859,
    "gift-line": 61860,
    "glove-fill": 61861,
    "glove-line": 61862,
    "golf-fill": 61863,
    "golf-line": 61864,
    "grill-fill": 61865,
    "grill-line": 61866,
    "group-fill": 61867,
    "group-line": 61868,
    "guitar-fill": 61869,
    "guitar-line": 61870,
    "gym-fill": 61871,
    "gym-line": 61872,
    "hadn-shake-fill": 61873,
    "hadn-shake-line": 61874,
    "hand-shake-fill": 61875,
    "hand-shake-line": 61876,
    "heart-fill": 61877,
    "heart-line": 61878,
    "heater-fill": 61879,
    "heater-line": 61880,
    "helicopter-fill": 61881,
    "helicopter-line": 61882,
    "horse-fill": 61883,
    "horse-line": 61884,
    "hotspot-fill": 61885,
    "hotspot-line": 61886,
    "hour-glass-fill": 61887,
    "hour-glass-line": 61888,
    "intercom-fill": 61889,
    "intercom-line": 61890,
    "internet-fill": 61891,
    "internet-line": 61892,
    "ironing-board-fill": 61893,
    "ironing-board-line": 61894,
    "jacuzzi-fill": 61895,
    "jacuzzi-line": 61896,
    "kettle-fill": 61897,
    "kettle-line": 61898,
    "keycard-fill": 61899,
    "keycard-line": 61900,
    "knife-fork-fill": 61901,
    "knife-fork-line": 61902,
    "langauge-fill": 61903,
    "langauge-line": 61904,
    "laptop-fill": 61905,
    "laptop-line": 61906,
    "lift-fill": 61907,
    "lift-line": 61908,
    "liquor-fill": 61909,
    "liquor-line": 61910,
    "lock-fill": 61911,
    "lock-line": 61912,
    "luggage-fill": 61913,
    "luggage-line": 61914,
    "mask-fill": 61915,
    "mask-line": 61916,
    "medical-fill": 61917,
    "medical-line": 61918,
    "menu-fill": 61919,
    "menu-line": 61920,
    "milk-fill": 61921,
    "milk-line": 61922,
    "mini-fridge-fill": 61923,
    "mini-fridge-line": 61924,
    "mirror-fill": 61925,
    "mirror-line": 61926,
    "mountain-fill": 61927,
    "mountain-line": 61928,
    "network-fill": 61929,
    "network-line": 61930,
    "newspaper-fill": 61931,
    "newspaper-line": 61932,
    "no-parking-fill": 61933,
    "no-parking-line": 61934,
    "no-smokin-fill": 61935,
    "no-smoking-line": 61936,
    "park-fill": 61937,
    "park-line": 61938,
    "parking-fill": 61939,
    "parking-line": 61940,
    "pet-fill": 61941,
    "pet-line": 61942,
    "phone-fill": 61943,
    "phone-line": 61944,
    "piano-fill": 61945,
    "piano-line": 61946,
    "pillow-fill": 61947,
    "pillow-line": 61948,
    "plug-fill": 61949,
    "plug-line": 61950,
    "pot-fill": 61951,
    "pot-line": 61952,
    "pray-fill": 61953,
    "pray-line": 61954,
    "presentation-fill": 61955,
    "presentation-line": 61956,
    "printer-fill": 61957,
    "printer-line": 61958,
    "recreational-vehicle-fill": 61959,
    "recreational-vehicle-line": 61960,
    "sauna-fill": 61961,
    "sauna-line": 61962,
    "scissor-fill": 61963,
    "scissor-line": 61964,
    "scrub-fill": 61965,
    "scrub-line": 61966,
    "security-fill": 61967,
    "security-line": 61968,
    "sewing-kit-fill": 61969,
    "sewing-kit-line": 61970,
    "shield-check-fill": 61971,
    "shield-check-line": 61972,
    "shoe-fill": 61973,
    "shoe-line": 61974,
    "shop-fill": 61975,
    "shop-line": 61976,
    "shopping-bag-fill": 61977,
    "shopping-bag-line": 61978,
    "shower-fill": 61979,
    "shower-line": 61980,
    "slipper-fill": 61981,
    "slipper-line": 61982,
    "smoking-fill": 61983,
    "smoking-line": 61984,
    "snow-flake-fill": 61985,
    "snow-flake-line": 61986,
    "sofa-2-fill": 61987,
    "sofa-2-line": 61988,
    "sofa-fill": 61989,
    "sofa-line": 61990,
    "sofa-set-fill": 61991,
    "sofa-set-line": 61992,
    "solarium-fill": 61993,
    "solarium-line": 61994,
    "spark-fill": 61995,
    "spark-line": 61996,
    "speaker-fill": 61997,
    "speaker-line": 61998,
    "spray-fill": 61999,
    "spray-line": 62000,
    "stairs-fill": 62001,
    "stairs-line": 62002,
    "storage-fill": 62003,
    "storage-line": 62004,
    "sun-set-fill": 62005,
    "sun-set-line": 62006,
    "support-fill": 62007,
    "support-line": 62008,
    "swimming-fill": 62009,
    "swimming-line": 62010,
    "swimming-pool-fill": 62011,
    "swimming-pool-line": 62012,
    "tapas-fill": 62013,
    "tapas-line": 62014,
    "terrace-fill": 62015,
    "terrace-line": 62016,
    "thermometer-fill": 62017,
    "thermometer-line": 62018,
    "ticket-fill": 62019,
    "ticket-line": 62020,
    "toilet-fill": 62021,
    "toilet-line": 62022,
    "toilet-paper-fill": 62023,
    "toilet-paper-line": 62024,
    "tooth-fill": 62025,
    "tooth-line": 62026,
    "towels-fill": 62027,
    "towels-line": 62028,
    "track-fill": 62029,
    "track-line": 62030,
    "train-fill": 62031,
    "train-line": 62032,
    "travel-agenc-fill": 62033,
    "travel-agency-line": 62034,
    "tree-fence-fill": 62035,
    "tree-fence-line": 62036,
    "trolly-fill": 62037,
    "trolly-line": 62038,
    "tshirt-fill": 62039,
    "tshirt-line": 62040,
    "tv-fill": 62041,
    "tv-line": 62042,
    "twin-bed-fill": 62043,
    "twin-bed-line": 62044,
    "umbrella-fill": 62045,
    "umbrella-line": 62046,
    "upgrade-fill": 62047,
    "upgrade-line": 62048,
    "vaccume-fill": 62049,
    "vaccume-line": 62050,
    "vault-fill": 62051,
    "vault-line": 62052,
    "vending-machine-fill": 62053,
    "vending-machine-line": 62054,
    "video-slash-fill": 62055,
    "video-slash-line": 62056,
    "video-tapes-fill": 62057,
    "video-tapes-line": 62058,
    "washing-machine-fill": 62059,
    "washing-machine-line": 62060,
    "water-furifier-fill": 62061,
    "water-furifier-line": 62062,
    "water-skiing-fill": 62063,
    "water-skiing-line": 62064,
    "wedding-fill": 62065,
    "wedding-line": 62066,
    "wheel-chair-fill": 62067,
    "wheel-chair-line": 62068,
    "wi-fi-fill": 62069,
    "wi-fi-line": 62070,
    "wine-glass-fill": 62071,
    "wine-glass-line": 62072,
    "wirlpool-fill": 62073,
    "wirlpool-line": 62074,
    "wrench-fill": 62075,
    "wrench-line": 62076
}